setup.cfg
setup.py
norecaptcha3/captcha.py
norecaptcha_python3.egg-info/PKG-INFO
norecaptcha_python3.egg-info/SOURCES.txt
norecaptcha_python3.egg-info/dependency_links.txt
norecaptcha_python3.egg-info/top_level.txt