Metadata-Version: 1.1
Name: norecaptcha-python3
Version: 1.0.0
Summary: Python 3 server-side library for google No CAPTCHA reCAPTCHA services.
Home-page: https://github.com/Zeioth/norecaptcha-python3
Author: Zeioth
Author-email: test@gmail.com
License: MIT
Platform: UNKNOWN
Classifier: Development Status :: 5 - Production/Stable
Classifier: Intended Audience :: Developers
Classifier: License :: OSI Approved :: MIT License
Classifier: Operating System :: OS Independent
